electbrian/__init__.py
electbrian/elects.py
electbrian-0.3.8.dist-info/METADATA
electbrian-0.3.8.dist-info/WHEEL
electbrian-0.3.8.dist-info/licenses/LICENSE
electbrian-0.3.8.dist-info/RECORD
