Metadata-Version: 2.4
Name: electbrian
Version: 0.3.8
Summary: Implements the point electrode approximation for electrodes
Project-URL: Repository, https://github.com/DennisToledo314/electbrian/
Author: Dennis Toledo
License-Expression: MIT
License-File: LICENSE
Requires-Python: >=3.7
